ganggu/__init__.py
ganggu/asynctask.py
ganggu/cipher.py
ganggu/datastructures.py
ganggu/datetimes.py
ganggu/flaskmate.py
ganggu/forms.py
ganggu/httpkit.py
ganggu/logkit.py
ganggu/redisstore.py
ganggu/rdbms/__init__.py
ganggu/rdbms/facility.py
ganggu/rdbms/reflect.py
ganggu/rdbms/schema.py
ganggu-0.9.4.dist-info/DESCRIPTION.rst
ganggu-0.9.4.dist-info/METADATA
ganggu-0.9.4.dist-info/RECORD
ganggu-0.9.4.dist-info/WHEEL
ganggu-0.9.4.dist-info/metadata.json
ganggu-0.9.4.dist-info/top_level.txt
